<?xml version="1.0" encoding="utf-8" ?><dwsync><file name="mc_explorer.html" server="claree.univ-lille1.fr//home/calciu/mc_slides/" local="3454856598" remote="16339799028" Dst="-1" /><file name="slides.htm" server="claree.univ-lille1.fr//home/calciu/mc_slides/" local="3483621307" remote="318763443876510972" Dst="-1" /><file name="slide-example.js" server="claree.univ-lille1.fr//home/calciu/mc_slides/" local="3482670529" remote="318763443875560272" Dst="-1" /><file name="slides2.htm" server="claree.univ-lille1.fr//home/calciu/mc_slides/" local="3606219322" remote="322704042133450244" Dst="-1" /><file name="apachecon.xsl" server="claree.univ-lille1.fr//home/calciu/mc_slides/" local="3241984740" remote="318763443875815512" Dst="-1" /><file name="adintro_ro.odt" server="claree.univ-lille1.fr//home/calciu/mc_slides/" local="3371054728" remote="318763443875815512" Dst="-1" /><file name="frame-outline.html" server="claree.univ-lille1.fr//home/calciu/mc_slides/" local="3241984740" remote="318763443875815512" Dst="-1" /><file name="frame_outline.html" server="claree.univ-lille1.fr//home/calciu/mc_slides/" local="3241984740" remote="318763443875815512" Dst="-1" /><file name="coursad1.pdf" server="claree.univ-lille1.fr//home/calciu/mc_slides/" local="3357832244" remote="318763443875815512" Dst="-1" /><file name="index.html" server="claree.univ-lille1.fr//home/calciu/mc_slides/" local="3241984740" remote="318763443875815512" Dst="-1" /><file name="navigation.xsl" server="claree.univ-lille1.fr//home/calciu/mc_slides/" local="3241984740" remote="318763443875815512" Dst="-1" /><file name="outline.xsl" server="claree.univ-lille1.fr//home/calciu/mc_slides/" local="3241984740" remote="318763443875815572" Dst="-1" /><file name="outline.xml" server="claree.univ-lille1.fr//home/calciu/mc_slides/" local="3241984740" remote="318763443875815572" Dst="-1" /><file name="slides.odt" server="claree.univ-lille1.fr//home/calciu/mc_slides/" local="3417968386" remote="318763443875815572" Dst="-1" /><file name="slides.xml" server="claree.univ-lille1.fr//home/calciu/mc_slides/" local="3241984740" remote="318763443875815572" Dst="-1" /><file name="slides.txt" server="claree.univ-lille1.fr//home/calciu/mc_slides/" local="3371049650" remote="318763443875815572" Dst="-1" /><file name="slides.pdf" server="claree.univ-lille1.fr//home/calciu/mc_slides/" local="3357825304" remote="318763443875815572" Dst="-1" /><file name="spinner.gif" server="claree.univ-lille1.fr//home/calciu/mc_slides/" local="3482414697" remote="318763443875815572" Dst="-1" /><file name="slides_mediawiki.txt" server="claree.univ-lille1.fr//home/calciu/mc_slides/" local="3371054960" remote="318763443875815572" Dst="-1" /><file name="WS_FTP.LOG" server="claree.univ-lille1.fr//home/calciu/mc_slides/" local="3241984740" remote="318763443875815572" Dst="-1" /></dwsync>